fermi_learn_lib/__init__.py
fermi_learn_lib/add_sub.py
fermi_fan_learn_lib-0.1.dist-info/LICENSE
fermi_fan_learn_lib-0.1.dist-info/METADATA
fermi_fan_learn_lib-0.1.dist-info/WHEEL
fermi_fan_learn_lib-0.1.dist-info/top_level.txt
fermi_fan_learn_lib-0.1.dist-info/RECORD
