Metadata-Version: 2.1
Name: fermi_fan_learn_lib
Version: 0.1
Summary: A library for Fermi-LAT FAN learning
Home-page: https://github.com/fermi-fan/tutorial
Author: fengpeng
Author-email: 765915617@qq.com
Classifier: Programming Language :: Python :: 3
Classifier: License :: OSI Approved :: MIT License
Classifier: Operating System :: OS Independent
Requires-Python: >=3.6
License-File: LICENSE
Requires-Dist: None
